deephys/__init__.py
deephys/deephys.py
deephys-0.14.1.dist-info/METADATA
deephys-0.14.1.dist-info/WHEEL
deephys-0.14.1.dist-info/top_level.txt
deephys-0.14.1.dist-info/RECORD
