Metadata-Version: 2.1
Name: deephys
Version: 0.14.1
Summary: Library to export neural activity to a Deephys-compatible format
Author-email: Matt Groth <mjgroth@mit.edu>
Project-URL: Homepage, https://deephys.org
Project-URL: Documentation, https://deephys.readthedocs.io/en/latest/
Project-URL: Bug Tracker, https://deephys.youtrack.cloud/
Requires-Dist: cbor2
Requires-Dist: numpy
Requires-Dist: tqdm
